aire/__init__.py
aire/errors.py
aire/utils.py
aire-0.0.2.dist-info/METADATA
aire-0.0.2.dist-info/WHEEL
aire-0.0.2.dist-info/RECORD
