Metadata-Version: 2.1
Name: aire
Version: 0.0.2
Summary: AI-powered re
Author: Kaloyan Aleksiev
Author-email: 67751757+kallyaleksiev@users.noreply.github.com
Requires-Python: >=3.12,<4.0
Classifier: Programming Language :: Python :: 3
Classifier: Programming Language :: Python :: 3.12
Requires-Dist: openai (>=1.52.2,<2.0.0)
